{
  "updated_at": "2026-01-29T15:30:00.872796+00:00",
  "last_24h": {
    "uptime_pct": 97.79,
    "healthy_checks": 398,
    "restart_events": 9,
    "total_checks": 407,
    "hours_analyzed": 24
  },
  "last_7d": {
    "uptime_pct": 97.69,
    "healthy_checks": 466,
    "restart_events": 11,
    "total_checks": 477,
    "hours_analyzed": 168
  },
  "daily": {
    "2026-01-29": {
      "uptime_pct": 97.46,
      "healthy": 192,
      "restarts": 5
    },
    "2026-01-28": {
      "uptime_pct": 97.86,
      "healthy": 274,
      "restarts": 6
    }
  }
}